[
    {
        "username": "aaqifahamed",
        "password": "bothalapitiya",
        "mobile": "0771112223",
        "userType": "User",
        "accountType": "Free"
    },
    {
        "username": "kavindu",
        "password": "university",
        "mobile": "0114445556",
        "userType": "User",
        "accountType": "Premium"
    },
    {
        "username": "miyuru",
        "password": "university",
        "mobile": "02135645565",
        "userType": "User",
        "accountType": "Premium"
    }
]